{
    "nodes": [
        {
            "name": " "
        },
        {
            "name": "Shot"
        },
        {
            "name": "Pass"
        },
        {
            "name": "Foul"
        },
        {
            "name": "TO"
        },
        {
            "name": "2P"
        },
        {
            "name": "3P"
        },
        {
            "name": "2P Make"
        },
        {
            "name": "2P Miss"
        },
        {
            "name": "3P Make"
        },
        {
            "name": "3P Miss"
        },
        {
            "name": "Assist"
        },
        {
            "name": "Bad Pass (Steal)"
        },
        {
            "name": "Bad Pass (OB)"
        },
        {
            "name": "Turnover"
        },
        {
            "name": "Getting Fouled"
        },
        {
            "name": "Offensive Foul"
        },
        {
            "name": "Shooting Foul"
        },
        {
            "name": "Dead Ball"
        },
        {
            "name": "FT Make"
        },
        {
            "name": "FT Miss"
        },
        {
            "name": "Charge"
        },
        {
            "name": "Loose Ball"
        }
    ],
    "links": [
        {
            "source": 0,
            "target": 1,
            "value": 1369
        },
        {
            "source": 0,
            "target": 2,
            "value": 551
        },
        {
            "source": 0,
            "target": 3,
            "value": 233
        },
        {
            "source": 0,
            "target": 4,
            "value": 250
        },
        {
            "source": 1,
            "target": 5,
            "value": 1245
        },
        {
            "source": 1,
            "target": 6,
            "value": 124
        },
        {
            "source": 5,
            "target": 7,
            "value": 803
        },
        {
            "source": 5,
            "target": 8,
            "value": 442
        },
        {
            "source": 6,
            "target": 9,
            "value": 34
        },
        {
            "source": 6,
            "target": 10,
            "value": 90
        },
        {
            "source": 2,
            "target": 11,
            "value": 476
        },
        {
            "source": 2,
            "target": 14,
            "value": 75
        },
        {
            "source": 14,
            "target": 12,
            "value": 55
        },
        {
            "source": 14,
            "target": 13,
            "value": 20
        },
        {
            "source": 3,
            "target": 15,
            "value": 210
        },
        {
            "source": 3,
            "target": 16,
            "value": 23
        },
        {
            "source": 15,
            "target": 17,
            "value": 83
        },
        {
            "source": 15,
            "target": 18,
            "value": 127
        },
        {
            "source": 17,
            "target": 19,
            "value": 83
        },
        {
            "source": 17,
            "target": 20,
            "value": 83
        },
        {
            "source": 16,
            "target": 21,
            "value": 22
        },
        {
            "source": 16,
            "target": 22,
            "value": 1
        }
    ]
}